orzo/__init__.py
orzo/core.py
orzo/delegates.py
orzo/programs.py
orzo/window.py
orzo/resources/arrow.obj
orzo/resources/cone.obj
orzo/resources/default.png
orzo/resources/skybox.png
orzo/resources/tab.obj
orzo/resources/torus.obj
orzo/shaders/base_vertex.glsl
orzo/shaders/bounding_sphere.glsl
orzo/shaders/instance_vertex.glsl
orzo/shaders/phong_fragment.glsl
orzo/shaders/select_fragment.glsl
orzo/shaders/sky.glsl
orzo-0.4.0.dist-info/WHEEL
orzo-0.4.0.dist-info/METADATA
orzo-0.4.0.dist-info/RECORD
