Metadata-Version: 2.1
Name: orzo
Version: 0.4.0
Summary: A python client application geared towards rendering 3D scenes with NOODLES
Keywords: noodles,cbor,Websockets,client,NOODLES
Author: Alex Racapé
Requires-Python: >=3.9
Classifier: Intended Audience :: Science/Research
Classifier: Programming Language :: Python :: 3
Classifier: Topic :: Scientific/Engineering :: Visualization
Requires-Dist: penne
Requires-Dist: numpy==1.25.0
Requires-Dist: numpy-quaternion==2022.4.3
Requires-Dist: moderngl==5.8.2
Requires-Dist: moderngl-window==2.4.4
Requires-Dist: imgui[pyglet]==2.0.0
Requires-Dist: pyglet==2.0.9
Requires-Dist: PyWavefront==1.3.3
Requires-Dist: Pillow==9.5.0
Requires-Dist: pytest ; extra == "testing"
Requires-Dist: rigatoni[geometry] ; extra == "testing"
Requires-Dist: pandas ; extra == "testing"
Project-URL: Documentation, https://insightcenternoodles.github.io/Orzo/
Project-URL: Source, https://github.com/InsightCenterNoodles/Orzo
Provides-Extra: testing
